libmoji/__init__.py
libmoji/libmoji.py
libmoji-0.0.5.dist-info/DESCRIPTION.rst
libmoji-0.0.5.dist-info/METADATA
libmoji-0.0.5.dist-info/RECORD
libmoji-0.0.5.dist-info/WHEEL
libmoji-0.0.5.dist-info/metadata.json
libmoji-0.0.5.dist-info/top_level.txt
