Metadata-Version: 2.0
Name: libmoji
Version: 0.0.5
Summary: Just a few emoji utilities
Home-page: https://github.com/michaelscript/libmoji
Author: Michael Green
Author-email: me@michaelgreen.net
License: MIT
Keywords: emoji,utilities,emoji loading,loading animation,emoji library,emoji framework,eloadji,load_moji,dumb library
Platform: UNKNOWN
Classifier: Development Status :: 3 - Alpha
Classifier: Intended Audience :: Developers
Classifier: Topic :: Software Development :: Libraries :: Python Modules
Classifier: License :: OSI Approved :: MIT License
Classifier: Programming Language :: Python :: 2
Classifier: Programming Language :: Python :: 2.6
Classifier: Programming Language :: Python :: 2.7
Classifier: Programming Language :: Python :: 3
Classifier: Programming Language :: Python :: 3.3
Classifier: Programming Language :: Python :: 3.4
Classifier: Programming Language :: Python :: 3.5
Requires-Dist: cursor (==1.1.0)
Requires-Dist: termcolor (==1.1.0)
